README.txt
setup.py
jasinja/__init__.py
jasinja/codegen.py
jasinja/compile.py
jasinja.egg-info/PKG-INFO
jasinja.egg-info/SOURCES.txt
jasinja.egg-info/dependency_links.txt
jasinja.egg-info/entry_points.txt
jasinja.egg-info/requires.txt
jasinja.egg-info/top_level.txt
jasinja/tests/__init__.py
jasinja/tests/run.py