Metadata-Version: 1.0
Name: jasinja
Version: 0.8.0
Summary: A JavaScript code generator for Jinja templates
Home-page: http://bitbucket.org/djc/jasinja
Author: Dirkjan Ochtman
Author-email: dirkjan@ochtman.nl
License: BSD
Platform: UNKNOWN
Classifier: Development Status :: 4 - Beta
Classifier: Environment :: Web Environment
Classifier: Intended Audience :: Developers
Classifier: License :: OSI Approved :: BSD License
Classifier: Operating System :: OS Independent
Classifier: Programming Language :: Python
Classifier: Topic :: Internet :: WWW/HTTP :: Dynamic Content
Classifier: Topic :: Software Development :: Libraries :: Python Modules
